FIFO.v
module FIFO(
    input      [7:0]     BUFFER_IN, 
    input                WR_EN, 
    input                RD_EN, 
    input                CLK, 
    input                RST,

    output reg [7:0]     BUFFER_OUT, 
    output reg           EMPTY, 
    output reg           FULL, 
    output reg [3:0]     COUNT
);
   
   reg[2:0] RD_PTR, WR_PTR;           
   reg[7:0] MEMORY[7:0];   

   always @(COUNT) begin
      EMPTY = (COUNT == 0);
      FULL  = (COUNT == 8);
   end

   always @(posedge CLK or posedge RST)
   begin
      if( RST )
         COUNT <= 0;

      else if( (!FULL && WR_EN) && ( !EMPTY && RD_EN ) )
         COUNT <= COUNT;

      else if( !FULL && WR_EN )
         COUNT <= COUNT + 1;

      else if( !EMPTY && RD_EN )
         COUNT <= COUNT - 1;
      else
         COUNT <= COUNT;
   end

   always @( posedge CLK or posedge RST)
   begin
      if( RST )
         BUFFER_OUT <= 0;
      else
      begin
         if( RD_EN && !EMPTY )
            BUFFER_OUT <= MEMORY[RD_PTR];

         else
            BUFFER_OUT <= BUFFER_OUT;

      end
   end

   always @(posedge CLK)
   begin

      if( WR_EN && !FULL )
         MEMORY[WR_PTR] <= BUFFER_IN;

      else
         MEMORY[WR_PTR] <= MEMORY[WR_PTR];
   end

   always@(posedge CLK or posedge RST)
   begin
      if( RST )
      begin
         WR_PTR <= 0;
         RD_PTR <= 0;
      end
      else
      begin
         if( !FULL && WR_EN )    WR_PTR <= WR_PTR + 1;
            else  WR_PTR <= WR_PTR;

         if( !EMPTY && RD_EN )   RD_PTR <= RD_PTR + 1;
         else RD_PTR <= RD_PTR;
      end

   end
endmodule

FIFO_tb.v
`timescale 1ns/10ps
`include "FIFO.v"

module FIFO_tb;
    reg  [7:0]     BUFFER_IN; 
    reg            WR_EN; 
    reg            RD_EN; 
    reg            CLK = 1; 
    reg            RST = 0;

    wire [7:0]     BUFFER_OUT; 
    wire           EMPTY; 
    wire           FULL;
    wire [3:0]     COUNT;

    FIFO fifo(
        BUFFER_IN, 
        WR_EN, 
        RD_EN, 
        CLK, 
        RST,

        BUFFER_OUT, 
        EMPTY, 
        FULL, 
        COUNT
    );

    // Setup simulation dump file
    initial begin
        $dumpfile("dump.vcd");
        $dumpvars(0, fifo);
    end

    // Setup clock
    always #1 CLK = ~CLK;

    initial begin
        RST = 1; #1 RST = 0;

        
        #1 WR_EN = 1;
        BUFFER_IN = 8'hF0;
        #1 WR_EN = 0;

        #1 WR_EN = 1;
        BUFFER_IN = 8'hF1;
        #1 WR_EN = 0;

        #1 WR_EN = 1;
        BUFFER_IN = 8'hF2;
        #1 WR_EN = 0;

        #1 WR_EN = 1;
        BUFFER_IN = 8'hF3;
        #1 WR_EN = 0;

        #1 WR_EN = 1;
        BUFFER_IN = 8'hF4;
        #1 WR_EN = 0;


        #1 WR_EN = 1;
        BUFFER_IN = 8'hF5;
        #1 WR_EN = 0;

        #1 WR_EN = 1;
        BUFFER_IN = 8'hF6;
        #1 WR_EN = 0;

        #1 WR_EN = 1;
        BUFFER_IN = 8'hF7;
        #1 WR_EN = 0;

        #1 RD_EN = 1;
        #1 RD_EN = 0;

        #1 RD_EN = 1;
        #1 RD_EN = 0;

        #2 $finish();
    end
endmodule

dump.vcd
$date
	Sun Jan 22 20:10:17 2023
$end
$version
	Icarus Verilog
$end
$timescale
	10ps
$end
$scope module FIFO_tb $end
$scope module fifo $end
$var wire 8 ! BUFFER_IN [7:0] $end
$var wire 1 " CLK $end
$var wire 1 # RD_EN $end
$var wire 1 $ RST $end
$var wire 1 % WR_EN $end
$var reg 8 & BUFFER_OUT [7:0] $end
$var reg 4 ' COUNT [3:0] $end
$var reg 1 ( EMPTY $end
$var reg 1 ) FULL $end
$var reg 3 * RD_PTR [2:0] $end
$var reg 3 + WR_PTR [2:0] $end
$upscope $end
$upscope $end
$enddefinitions $end
#0
$dumpvars
b0 +
b0 *
0)
1(
b0 '
b0 &
x%
1$
x#
1"
bx !
$end
#100
0$
0"
#200
0(
b1 +
b1 '
b11110000 !
1%
1"
#300
0%
0"
#400
b10 '
b10 +
b11110001 !
1%
1"
#500
0%
0"
#600
b11 +
b11 '
b11110010 !
1%
1"
#700
0%
0"
#800
b100 '
b100 +
b11110011 !
1%
1"
#900
0%
0"
#1000
b101 +
b101 '
b11110100 !
1%
1"
#1100
0%
0"
#1200
b110 '
b110 +
b11110101 !
1%
1"
#1300
0%
0"
#1400
b111 +
b111 '
b11110110 !
1%
1"
#1500
0%
0"
#1600
1)
b1000 '
b0 +
b11110111 !
1%
1"
#1700
0%
0"
#1800
0)
b1 *
b11110000 &
b111 '
1#
1"
#1900
0#
0"
#2000
b110 '
b11110001 &
b10 *
1#
1"
#2100
0#
0"
